dokuwikixmlrpc.py
dokuwikixmlrpc-2022.12.22.dist-info/LICENSE.txt
dokuwikixmlrpc-2022.12.22.dist-info/METADATA
dokuwikixmlrpc-2022.12.22.dist-info/WHEEL
dokuwikixmlrpc-2022.12.22.dist-info/top_level.txt
dokuwikixmlrpc-2022.12.22.dist-info/RECORD
