Metadata-Version: 2.1
Name: dokuwikixmlrpc
Version: 2022.12.22
Summary: DokuWiki XML-RPC module.
Home-page: https://github.com/kynan/dokuwikixmlrpc
Download-URL: https://github.com/downloads/kynan/dokuwikixmlrpc/dokuwikixmlrpc.tgz
Author: Michael Klier
Author-email: chi@chimeric.de
Maintainer: Florian Rathgeber
Maintainer-email: florian.rathgeber@gmail.com
License: License :: OSI Approved :: MIT License
Classifier: Development Status :: 4 - Beta
Classifier: Environment :: Other Environment
Classifier: Intended Audience :: Developers
Classifier: Operating System :: OS Independent
Classifier: Programming Language :: Python
Classifier: Programming Language :: Python :: 2
Classifier: Programming Language :: Python :: 2.7
Classifier: Programming Language :: Python :: 3
Classifier: Programming Language :: Python :: 3.5
Classifier: Programming Language :: Python :: 3.6
Classifier: Programming Language :: Python :: 3.7
Classifier: Programming Language :: Python :: 3.8
Classifier: Topic :: Software Development :: Libraries :: Python Modules
License-File: LICENSE.txt
